abalyzer/__init__.py
abalyzer/parser.py
abalyzer/data/__init__.py
abalyzer/data/generate_data/__init__.py
abalyzer/data/generate_data/__main__.py
abalyzer/data/generate_data/duplicate_entry_remover.py
abalyzer/data/generate_data/get_aba_numbers_scraper.py
abalyzer/data/generate_data/website_list_cleaner.py
abalyzer-0.0.1.dist-info/LICENSE.txt
abalyzer-0.0.1.dist-info/METADATA
abalyzer-0.0.1.dist-info/WHEEL
abalyzer-0.0.1.dist-info/top_level.txt
abalyzer-0.0.1.dist-info/RECORD
