Metadata-Version: 2.1
Name: abalyzer
Version: 0.0.1
Summary: Parses ABA (American Bankers Association) codes
Home-page: https://github.com/shivanprasad/abalyzer
Author: Shivan Prasad
Project-URL: Bug Tracker, https://github.com/shivanprasad/abalyzer/issues
Classifier: Programming Language :: Python :: 3
Classifier: License :: OSI Approved :: MIT License
Classifier: Operating System :: OS Independent
Requires-Python: >=3.6
License-File: LICENSE.txt
